aws_secrets_wrapper/__init__.py
aws_secrets_wrapper/cli.py
aws_secrets_wrapper/lambda_function.py
aws_secrets_wrapper/wrap.py
aws_secrets_wrapper-0.1.3.dist-info/METADATA
aws_secrets_wrapper-0.1.3.dist-info/WHEEL
aws_secrets_wrapper-0.1.3.dist-info/entry_points.txt
aws_secrets_wrapper-0.1.3.dist-info/RECORD
